nssacPreCommitHook/__init__.py
nssacPreCommitHook/configuration.py
nssacPreCommitHook/header.py
nssacPreCommitHook/preCommitHook.py
nssacPreCommitHook/git/__init__.py
nssacPreCommitHook/git/git.py
nssacPreCommitHook/git/status.py
nssacPreCommitHook-1.0.4.data/scripts/preCommitHook.py
nssacPreCommitHook-1.0.4.dist-info/LICENSE
nssacPreCommitHook-1.0.4.dist-info/METADATA
nssacPreCommitHook-1.0.4.dist-info/WHEEL
nssacPreCommitHook-1.0.4.dist-info/top_level.txt
nssacPreCommitHook-1.0.4.dist-info/RECORD
