Metadata-Version: 2.1
Name: nssacPreCommitHook
Version: 1.0.4
Summary: A pre commit hook used to maintain license and copyright information in source files.
Home-page: http://github.com/NSSAC/nssacPreCommitHook
Author: Stefan Hoops
Author-email: shoops@virginia.edu
License: Apache 2.0
Platform: UNKNOWN
Classifier: Programming Language :: Python :: 3
Classifier: License :: OSI Approved :: Apache Software License
Classifier: Operating System :: OS Independent
License-File: LICENSE
Requires-Dist: jsonschema
Requires-Dist: pathspec
